UliPlot/Figure.py
UliPlot/Size.py
UliPlot/Style.py
UliPlot/TickFormat.py
UliPlot/Ticks.py
UliPlot/XLSX.py
UliPlot/__init__.py
uliplot-0.2.4.dist-info/LICENSE
uliplot-0.2.4.dist-info/METADATA
uliplot-0.2.4.dist-info/WHEEL
uliplot-0.2.4.dist-info/RECORD
